[
 {
  "directory": "/home/egache/work/cpp09/ex00",
  "arguments": [
   "c++",
   "-Wall",
   "-Wextra",
   "-Werror",
   "-g3",
   "-std=c++98",
   "-Iincludes",
   "-MMD",
   "-MP",
   "-c",
   "-o",
   ".build/main.o",
   "src/main.cpp"
  ],
  "file": "src/main.cpp"
 },
 {
  "directory": "/home/egache/work/cpp09/ex00",
  "arguments": [
   "c++",
   "-Wall",
   "-Wextra",
   "-Werror",
   "-g3",
   "-std=c++98",
   "-Iincludes",
   "-MMD",
   "-MP",
   "-c",
   "-o",
   ".build/BitcoinExchange.o",
   "src/BitcoinExchange.cpp"
  ],
  "file": "src/BitcoinExchange.cpp"
 }
]
